DPI-MPI-MESH/test/alu_tile.v
`timescale 1ns/1ps

module alu_tile #(
    parameter integer TILE_X = 0,
    parameter integer TILE_Y = 0
)(
    input  wire [63:0] a,
    input  wire [63:0] b,
    input  wire [3:0]  mode,    // global mode (0..8 used)
    output reg  [63:0] result_out,
    output reg         match    // high if tile's assigned code == mode
);

    // compute this tile's assigned mode code
    localparam integer ASSIGNED = (TILE_Y * 3) + TILE_X; // 0..8

    // internal op result (combinational)
    reg [63:0] op_result;

    always @(*) begin
        // default
        op_result = 64'd0;

        // compute op based on mode (tiles compute all ops when asked)
        case (mode)
            4'd0: op_result = a + b;                       // add
            4'd1: op_result = a - b;                       // sub
            4'd2: op_result = a * b;                       // mul (low 64)
            4'd3: op_result = (b == 0) ? 64'd0 : (a / b);  // div (unsigned, safe)
            4'd4: op_result = a & b;                       // and
            4'd5: op_result = a | b;                       // or
            4'd6: op_result = a ^ b;                       // xor
            4'd7: op_result = a << b[5:0];                 // shl (use low 6 bits)
            4'd8: op_result = a >> b[5:0];                 // shr (logical)
            default: op_result = 64'd0;
        endcase

        // only drive output when this tile's assigned mode equals global mode
        if (mode == ASSIGNED[3:0]) begin
            result_out = op_result;
            match = 1'b1;
        end else begin
            result_out = 64'd0;
            match = 1'b0;
        end
    end

endmodule

DPI-MPI-MESH/test/calculator_grid.v
`timescale 1ns/1ps

module calculator_grid(
    input  wire [63:0] a,
    input  wire [63:0] b,
    input  wire [3:0]  mode,
    output wire [63:0] out_result,
    output wire        out_valid
);

    // Instantiate 3x3 grid of alu_tiles
    wire [63:0] tile_res [0:8];
    wire        tile_match[0:8];

    genvar gx, gy;
    integer idx = 0;

    // manual unroll (easier to read) for 3x3
    alu_tile #(.TILE_X(0), .TILE_Y(0)) tile00(.a(a), .b(b), .mode(mode), .result_out(tile_res[0]), .match(tile_match[0]));
    alu_tile #(.TILE_X(1), .TILE_Y(0)) tile10(.a(a), .b(b), .mode(mode), .result_out(tile_res[1]), .match(tile_match[1]));
    alu_tile #(.TILE_X(2), .TILE_Y(0)) tile20(.a(a), .b(b), .mode(mode), .result_out(tile_res[2]), .match(tile_match[2]));

    alu_tile #(.TILE_X(0), .TILE_Y(1)) tile01(.a(a), .b(b), .mode(mode), .result_out(tile_res[3]), .match(tile_match[3]));
    alu_tile #(.TILE_X(1), .TILE_Y(1)) tile11(.a(a), .b(b), .mode(mode), .result_out(tile_res[4]), .match(tile_match[4]));
    alu_tile #(.TILE_X(2), .TILE_Y(1)) tile21(.a(a), .b(b), .mode(mode), .result_out(tile_res[5]), .match(tile_match[5]));

    alu_tile #(.TILE_X(0), .TILE_Y(2)) tile02(.a(a), .b(b), .mode(mode), .result_out(tile_res[6]), .match(tile_match[6]));
    alu_tile #(.TILE_X(1), .TILE_Y(2)) tile12(.a(a), .b(b), .mode(mode), .result_out(tile_res[7]), .match(tile_match[7]));
    alu_tile #(.TILE_X(2), .TILE_Y(2)) tile22(.a(a), .b(b), .mode(mode), .result_out(tile_res[8]), .match(tile_match[8]));

    // select the tile whose match is high
    reg [63:0] selected;
    reg sel_valid;
    integer i;

    always @(*) begin
        selected = 64'd0;
        sel_valid = 1'b0;
        for (i = 0; i < 9; i = i + 1) begin
            if (tile_match[i]) begin
                selected = tile_res[i];
                sel_valid = 1'b1;
            end
        end
    end

    assign out_result = selected;
    assign out_valid  = sel_valid;

endmodule

DPI-MPI-MESH/test/calculator.v
// 3x3 ALU Grid + Calculator top
// Single-file Verilog design implementing:
//  - alu_tile: can compute 9 operations but only drives output when the global mode matches
//               its assigned (x,y) position.
//  - calculator_grid: instantiates a 3x3 grid of alu_tile modules (x=0..2, y=0..2).
//  - calculator (top): takes inputs a,b,mode and produces result and valid.
//
// Mode mapping (4-bit mode, values 0..8): row-major, (x=0..2, y=0..2)
//   mode = y*3 + x
//   0: (0,0)  1: (1,0)  2: (2,0)
//   3: (0,1)  4: (1,1)  5: (2,1)
//   6: (0,2)  7: (1,2)  8: (2,2)
//
// Supported operations (selected by the same mode value inside each tile):
//  0: add    -> a + b
//  1: sub    -> a - b
//  2: mul    -> a * b (lower 64 bits)
//  3: div    -> a / b (unsigned, 0 on div-by-zero)
//  4: and    -> a & b
//  5: or     -> a | b
//  6: xor    -> a ^ b
//  7: shl    -> a << (b[5:0]) (shift by low 6 bits)
//  8: shr    -> a >> (b[5:0]) (logical shift)
//
// Notes:
//  - Width: 64-bit datapath for a, b, result. Mode is 4 bits.
//  - Each alu_tile computes the operation selected by the incoming global mode,
//    but will only assert its 'match' output and drive result_out when the
//    global mode equals its tile_id (y*3 + x). This matches "only do the mode
//    which aligns with their x,y position" while still being able to compute all ops.
//  - calculator selects the matching tile's result and asserts valid.
//
// Testbench included at bottom (use `iverilog -DTESTBENCH 3x3_ALU_Calculator.v && vvp a.out`)

`timescale 1ns/1ps

// Top-level calculator module (exposed interface)
module calculator(
    input  wire [63:0] a,
    input  wire [63:0] b,
    input  wire [3:0]  mode,
    output wire [63:0] result,
    output wire        valid
);

    calculator_grid grid(.a(a), .b(b), .mode(mode), .out_result(result), .out_valid(valid));

endmodule

DPI-MPI-MESH/test/tb_calculator.vcd
$version Generated by VerilatedVcd $end
$timescale 1ps $end
 $scope module TOP $end
  $var wire 64 n a [63:0] $end
  $var wire 64 p b [63:0] $end
  $var wire 4 r mode [3:0] $end
  $var wire 64 s result [63:0] $end
  $var wire 1 u valid $end
  $scope module calculator $end
   $var wire 64 n a [63:0] $end
   $var wire 64 p b [63:0] $end
   $var wire 4 r mode [3:0] $end
   $var wire 64 s result [63:0] $end
   $var wire 1 u valid $end
   $scope module grid $end
    $var wire 64 n a [63:0] $end
    $var wire 64 p b [63:0] $end
    $var wire 4 r mode [3:0] $end
    $var wire 64 s out_result [63:0] $end
    $var wire 1 u out_valid $end
    $var wire 64 # tile_res[0] [63:0] $end
    $var wire 64 % tile_res[1] [63:0] $end
    $var wire 64 ' tile_res[2] [63:0] $end
    $var wire 64 ) tile_res[3] [63:0] $end
    $var wire 64 + tile_res[4] [63:0] $end
    $var wire 64 - tile_res[5] [63:0] $end
    $var wire 64 / tile_res[6] [63:0] $end
    $var wire 64 1 tile_res[7] [63:0] $end
    $var wire 64 3 tile_res[8] [63:0] $end
    $var wire 1 5 tile_match[0] $end
    $var wire 1 6 tile_match[1] $end
    $var wire 1 7 tile_match[2] $end
    $var wire 1 8 tile_match[3] $end
    $var wire 1 9 tile_match[4] $end
    $var wire 1 : tile_match[5] $end
    $var wire 1 ; tile_match[6] $end
    $var wire 1 < tile_match[7] $end
    $var wire 1 = tile_match[8] $end
    $var wire 32 v idx [31:0] $end
    $var wire 64 > selected [63:0] $end
    $var wire 1 @ sel_valid $end
    $var wire 32 w i [31:0] $end
    $scope module tile00 $end
     $var wire 32 x TILE_X [31:0] $end
     $var wire 32 x TILE_Y [31:0] $end
     $var wire 64 n a [63:0] $end
     $var wire 64 p b [63:0] $end
     $var wire 4 r mode [3:0] $end
     $var wire 64 A result_out [63:0] $end
     $var wire 1 C match $end
     $var wire 32 x ASSIGNED [31:0] $end
     $var wire 64 D op_result [63:0] $end
    $upscope $end
    $scope module tile01 $end
     $var wire 32 x TILE_X [31:0] $end
     $var wire 32 y TILE_Y [31:0] $end
     $var wire 64 n a [63:0] $end
     $var wire 64 p b [63:0] $end
     $var wire 4 r mode [3:0] $end
     $var wire 64 F result_out [63:0] $end
     $var wire 1 H match $end
     $var wire 32 z ASSIGNED [31:0] $end
     $var wire 64 I op_result [63:0] $end
    $upscope $end
    $scope module tile02 $end
     $var wire 32 x TILE_X [31:0] $end
     $var wire 32 { TILE_Y [31:0] $end
     $var wire 64 n a [63:0] $end
     $var wire 64 p b [63:0] $end
     $var wire 4 r mode [3:0] $end
     $var wire 64 K result_out [63:0] $end
     $var wire 1 M match $end
     $var wire 32 | ASSIGNED [31:0] $end
     $var wire 64 N op_result [63:0] $end
    $upscope $end
    $scope module tile10 $end
     $var wire 32 y TILE_X [31:0] $end
     $var wire 32 x TILE_Y [31:0] $end
     $var wire 64 n a [63:0] $end
     $var wire 64 p b [63:0] $end
     $var wire 4 r mode [3:0] $end
     $var wire 64 P result_out [63:0] $end
     $var wire 1 R match $end
     $var wire 32 y ASSIGNED [31:0] $end
     $var wire 64 S op_result [63:0] $end
    $upscope $end
    $scope module tile11 $end
     $var wire 32 y TILE_X [31:0] $end
     $var wire 32 y TILE_Y [31:0] $end
     $var wire 64 n a [63:0] $end
     $var wire 64 p b [63:0] $end
     $var wire 4 r mode [3:0] $end
     $var wire 64 U result_out [63:0] $end
     $var wire 1 W match $end
     $var wire 32 } ASSIGNED [31:0] $end
     $var wire 64 X op_result [63:0] $end
    $upscope $end
    $scope module tile12 $end
     $var wire 32 y TILE_X [31:0] $end
     $var wire 32 { TILE_Y [31:0] $end
     $var wire 64 n a [63:0] $end
     $var wire 64 p b [63:0] $end
     $var wire 4 r mode [3:0] $end
     $var wire 64 Z result_out [63:0] $end
     $var wire 1 \ match $end
     $var wire 32 ~ ASSIGNED [31:0] $end
     $var wire 64 ] op_result [63:0] $end
    $upscope $end
    $scope module tile20 $end
     $var wire 32 { TILE_X [31:0] $end
     $var wire 32 x TILE_Y [31:0] $end
     $var wire 64 n a [63:0] $end
     $var wire 64 p b [63:0] $end
     $var wire 4 r mode [3:0] $end
     $var wire 64 _ result_out [63:0] $end
     $var wire 1 a match $end
     $var wire 32 { ASSIGNED [31:0] $end
     $var wire 64 b op_result [63:0] $end
    $upscope $end
    $scope module tile21 $end
     $var wire 32 { TILE_X [31:0] $end
     $var wire 32 y TILE_Y [31:0] $end
     $var wire 64 n a [63:0] $end
     $var wire 64 p b [63:0] $end
     $var wire 4 r mode [3:0] $end
     $var wire 64 d result_out [63:0] $end
     $var wire 1 f match $end
     $var wire 32 !! ASSIGNED [31:0] $end
     $var wire 64 g op_result [63:0] $end
    $upscope $end
    $scope module tile22 $end
     $var wire 32 { TILE_X [31:0] $end
     $var wire 32 { TILE_Y [31:0] $end
     $var wire 64 n a [63:0] $end
     $var wire 64 p b [63:0] $end
     $var wire 4 r mode [3:0] $end
     $var wire 64 i result_out [63:0] $end
     $var wire 1 k match $end
     $var wire 32 "! ASSIGNED [31:0] $end
     $var wire 64 l op_result [63:0] $end
    $upscope $end
   $upscope $end
  $upscope $end
 $upscope $end
$enddefinitions $end


#0
b0000000000000000000000000000000000000000000000000000000000010111 #
b0000000000000000000000000000000000000000000000000000000000000000 %
b0000000000000000000000000000000000000000000000000000000000000000 '
b0000000000000000000000000000000000000000000000000000000000000000 )
b0000000000000000000000000000000000000000000000000000000000000000 +
b0000000000000000000000000000000000000000000000000000000000000000 -
b0000000000000000000000000000000000000000000000000000000000000000 /
b0000000000000000000000000000000000000000000000000000000000000000 1
b0000000000000000000000000000000000000000000000000000000000000000 3
15
06
07
08
09
0:
0;
0<
0=
b0000000000000000000000000000000000000000000000000000000000010111 >
1@
b0000000000000000000000000000000000000000000000000000000000010111 A
1C
b0000000000000000000000000000000000000000000000000000000000010111 D
b0000000000000000000000000000000000000000000000000000000000000000 F
0H
b0000000000000000000000000000000000000000000000000000000000010111 I
b0000000000000000000000000000000000000000000000000000000000000000 K
0M
b0000000000000000000000000000000000000000000000000000000000010111 N
b0000000000000000000000000000000000000000000000000000000000000000 P
0R
b0000000000000000000000000000000000000000000000000000000000010111 S
b0000000000000000000000000000000000000000000000000000000000000000 U
0W
b0000000000000000000000000000000000000000000000000000000000010111 X
b0000000000000000000000000000000000000000000000000000000000000000 Z
0\
b0000000000000000000000000000000000000000000000000000000000010111 ]
b0000000000000000000000000000000000000000000000000000000000000000 _
0a
b0000000000000000000000000000000000000000000000000000000000010111 b
b0000000000000000000000000000000000000000000000000000000000000000 d
0f
b0000000000000000000000000000000000000000000000000000000000010111 g
b0000000000000000000000000000000000000000000000000000000000000000 i
0k
b0000000000000000000000000000000000000000000000000000000000010111 l
b0000000000000000000000000000000000000000000000000000000000010100 n
b0000000000000000000000000000000000000000000000000000000000000011 p
b0000 r
b0000000000000000000000000000000000000000000000000000000000010111 s
1u
b00000000000000000000000000000000 v
b00000000000000000000000000001001 w
b00000000000000000000000000000000 x
b00000000000000000000000000000001 y
b00000000000000000000000000000011 z
b00000000000000000000000000000010 {
b00000000000000000000000000000110 |
b00000000000000000000000000000100 }
b00000000000000000000000000000111 ~
b00000000000000000000000000000101 !!
b00000000000000000000000000001000 "!
#1
b0000000000000000000000000000000000000000000000000000000000000000 #
b0000000000000000000000000000000000000000000000000000000000010001 %
05
16
b0000000000000000000000000000000000000000000000000000000000010001 >
b0000000000000000000000000000000000000000000000000000000000000000 A
0C
b0000000000000000000000000000000000000000000000000000000000010001 D
b0000000000000000000000000000000000000000000000000000000000010001 I
b0000000000000000000000000000000000000000000000000000000000010001 N
b0000000000000000000000000000000000000000000000000000000000010001 P
1R
b0000000000000000000000000000000000000000000000000000000000010001 S
b0000000000000000000000000000000000000000000000000000000000010001 X
b0000000000000000000000000000000000000000000000000000000000010001 ]
b0000000000000000000000000000000000000000000000000000000000010001 b
b0000000000000000000000000000000000000000000000000000000000010001 g
b0000000000000000000000000000000000000000000000000000000000010001 l
b0001 r
b0000000000000000000000000000000000000000000000000000000000010001 s
#2
b0000000000000000000000000000000000000000000000000000000000000000 %
b0000000000000000000000000000000000000000000000000000000000111100 '
06
17
b0000000000000000000000000000000000000000000000000000000000111100 >
b0000000000000000000000000000000000000000000000000000000000111100 D
b0000000000000000000000000000000000000000000000000000000000111100 I
b0000000000000000000000000000000000000000000000000000000000111100 N
b0000000000000000000000000000000000000000000000000000000000000000 P
0R
b0000000000000000000000000000000000000000000000000000000000111100 S
b0000000000000000000000000000000000000000000000000000000000111100 X
b0000000000000000000000000000000000000000000000000000000000111100 ]
b0000000000000000000000000000000000000000000000000000000000111100 _
1a
b0000000000000000000000000000000000000000000000000000000000111100 b
b0000000000000000000000000000000000000000000000000000000000111100 g
b0000000000000000000000000000000000000000000000000000000000111100 l
b0010 r
b0000000000000000000000000000000000000000000000000000000000111100 s
#3
b0000000000000000000000000000000000000000000000000000000000000000 '
b0000000000000000000000000000000000000000000000000000000000000110 )
07
18
b0000000000000000000000000000000000000000000000000000000000000110 >
b0000000000000000000000000000000000000000000000000000000000000110 D
b0000000000000000000000000000000000000000000000000000000000000110 F
1H
b0000000000000000000000000000000000000000000000000000000000000110 I
b0000000000000000000000000000000000000000000000000000000000000110 N
b0000000000000000000000000000000000000000000000000000000000000110 S
b0000000000000000000000000000000000000000000000000000000000000110 X
b0000000000000000000000000000000000000000000000000000000000000110 ]
b0000000000000000000000000000000000000000000000000000000000000000 _
0a
b0000000000000000000000000000000000000000000000000000000000000110 b
b0000000000000000000000000000000000000000000000000000000000000110 g
b0000000000000000000000000000000000000000000000000000000000000110 l
b0011 r
b0000000000000000000000000000000000000000000000000000000000000110 s
#4
b0000000000000000000000000000000000000000000000000000000000000000 )
08
19
b0000000000000000000000000000000000000000000000000000000000000000 >
b0000000000000000000000000000000000000000000000000000000000000000 D
b0000000000000000000000000000000000000000000000000000000000000000 F
0H
b0000000000000000000000000000000000000000000000000000000000000000 I
b0000000000000000000000000000000000000000000000000000000000000000 N
b0000000000000000000000000000000000000000000000000000000000000000 S
1W
b0000000000000000000000000000000000000000000000000000000000000000 X
b0000000000000000000000000000000000000000000000000000000000000000 ]
b0000000000000000000000000000000000000000000000000000000000000000 b
b0000000000000000000000000000000000000000000000000000000000000000 g
b0000000000000000000000000000000000000000000000000000000000000000 l
b0100 r
b0000000000000000000000000000000000000000000000000000000000000000 s
#5
b0000000000000000000000000000000000000000000000000000000000010111 -
09
1:
b0000000000000000000000000000000000000000000000000000000000010111 >
b0000000000000000000000000000000000000000000000000000000000010111 D
b0000000000000000000000000000000000000000000000000000000000010111 I
b0000000000000000000000000000000000000000000000000000000000010111 N
b0000000000000000000000000000000000000000000000000000000000010111 S
0W
b0000000000000000000000000000000000000000000000000000000000010111 X
b0000000000000000000000000000000000000000000000000000000000010111 ]
b0000000000000000000000000000000000000000000000000000000000010111 b
b0000000000000000000000000000000000000000000000000000000000010111 d
1f
b0000000000000000000000000000000000000000000000000000000000010111 g
b0000000000000000000000000000000000000000000000000000000000010111 l
b0101 r
b0000000000000000000000000000000000000000000000000000000000010111 s
#6
b0000000000000000000000000000000000000000000000000000000000000000 -
b0000000000000000000000000000000000000000000000000000000000010111 /
0:
1;
b0000000000000000000000000000000000000000000000000000000000010111 K
1M
b0000000000000000000000000000000000000000000000000000000000000000 d
0f
b0110 r
#7
b0000000000000000000000000000000000000000000000000000000000000000 /
b0000000000000000000000000000000000000000000000000000000010100000 1
0;
1<
b0000000000000000000000000000000000000000000000000000000010100000 >
b0000000000000000000000000000000000000000000000000000000010100000 D
b0000000000000000000000000000000000000000000000000000000010100000 I
b0000000000000000000000000000000000000000000000000000000000000000 K
0M
b0000000000000000000000000000000000000000000000000000000010100000 N
b0000000000000000000000000000000000000000000000000000000010100000 S
b0000000000000000000000000000000000000000000000000000000010100000 X
b0000000000000000000000000000000000000000000000000000000010100000 Z
1\
b0000000000000000000000000000000000000000000000000000000010100000 ]
b0000000000000000000000000000000000000000000000000000000010100000 b
b0000000000000000000000000000000000000000000000000000000010100000 g
b0000000000000000000000000000000000000000000000000000000010100000 l
b0111 r
b0000000000000000000000000000000000000000000000000000000010100000 s
#8
b0000000000000000000000000000000000000000000000000000000000000000 1
b0000000000000000000000000000000000000000000000000000000000000010 3
0<
1=
b0000000000000000000000000000000000000000000000000000000000000010 >
b0000000000000000000000000000000000000000000000000000000000000010 D
b0000000000000000000000000000000000000000000000000000000000000010 I
b0000000000000000000000000000000000000000000000000000000000000010 N
b0000000000000000000000000000000000000000000000000000000000000010 S
b0000000000000000000000000000000000000000000000000000000000000010 X
b0000000000000000000000000000000000000000000000000000000000000000 Z
0\
b0000000000000000000000000000000000000000000000000000000000000010 ]
b0000000000000000000000000000000000000000000000000000000000000010 b
b0000000000000000000000000000000000000000000000000000000000000010 g
b0000000000000000000000000000000000000000000000000000000000000010 i
1k
b0000000000000000000000000000000000000000000000000000000000000010 l
b1000 r
b0000000000000000000000000000000000000000000000000000000000000010 s
#9
b0000000000000000000000000000000000000000000000000000000000000000 3
19
0=
b0000000000000000000000000000000000000000000000000000000000000000 >
b0000000000000000000000000000000000000000000000000000000000000000 D
b0000000000000000000000000000000000000000000000000000000000000000 I
b0000000000000000000000000000000000000000000000000000000000000000 N
b0000000000000000000000000000000000000000000000000000000000000000 S
1W
b0000000000000000000000000000000000000000000000000000000000000000 X
b0000000000000000000000000000000000000000000000000000000000000000 ]
b0000000000000000000000000000000000000000000000000000000000000000 b
b0000000000000000000000000000000000000000000000000000000000000000 g
b0000000000000000000000000000000000000000000000000000000000000000 i
0k
b0000000000000000000000000000000000000000000000000000000000000000 l
b0100 r
b0000000000000000000000000000000000000000000000000000000000000000 s
#10
09
1<
0W
1\
b0000000000000000000000000000000011111111000000001111111100000000 n
b0000000000000000000000000000000000000000111111110000000011111111 p
b0111 r
